LICENSE
MANIFEST.in
README.md
setup.py
django_sts.egg-info/PKG-INFO
django_sts.egg-info/SOURCES.txt
django_sts.egg-info/dependency_links.txt
django_sts.egg-info/requires.txt
django_sts.egg-info/top_level.txt
sts/__init__.py
sts/admin.py
sts/contextmanagers.py
sts/models.py
sts/shortcuts.py
sts/urls.py
sts/utils.py
sts/views.py
sts/fixtures/initial_data.json
sts/migrations/0001_initial.py
sts/migrations/0002_auto__chg_field_transition_event.py
sts/migrations/0003_convert_duration_to_milliseconds.py
sts/migrations/0004_auto__add_field_transition_message.py
sts/migrations/0005_auto__add_field_transition_failed.py
sts/migrations/0006_convert_failed_null_to_false.py
sts/migrations/0007_auto__chg_field_transition_failed.py
sts/migrations/__init__.py
sts/static/sts/css/style.css
sts/static/sts/js/sts.js
sts/templates/sts/base.html
sts/templates/sts/systems.html