Metadata-Version: 1.0
Name: django-sts
Version: 0.7.3
Summary: State Transition System for Django
Home-page: https://github.com/cbmi/django-sts/
Author: Byron Ruth
Author-email: b@devel.io
License: BSD
Keywords: FSM state machine transition Django
Platform: UNKNOWN
Classifier: Development Status :: 4 - Beta
Classifier: License :: OSI Approved :: BSD License
Classifier: Programming Language :: Python :: 2.6
Classifier: Programming Language :: Python :: 2.7
Classifier: Framework :: Django
Classifier: Intended Audience :: Developers
Classifier: Intended Audience :: Science/Research
Classifier: Intended Audience :: Information Technology
